{
  "scan_time": "2026-07-04 10:00",
  "triggers_fired": [],
  "stops_triggered": [],
  "watchlist_approaching": [
    {
      "ticker": "METC",
      "account": "aggressive",
      "current": 12.95,
      "trigger": 13.0,
      "gap_pct": -0.4,
      "priority": "B",
      "status": "entered"
    },
    {
      "ticker": "VST",
      "account": "institutional",
      "current": 151.05,
      "trigger": 150.0,
      "gap_pct": 0.7,
      "priority": "A",
      "status": "entered"
    },
    {
      "ticker": "MLEC",
      "account": "aggressive",
      "current": 7.965,
      "trigger": 7.5,
      "gap_pct": 6.2,
      "priority": "B",
      "status": "entered"
    },
    {
      "ticker": "PLTR",
      "account": "blueshrimp",
      "current": 129.8,
      "trigger": 120.0,
      "gap_pct": 8.2,
      "priority": "A",
      "status": "entered"
    }
  ],
  "portfolio_summary": {
    "institutional": {
      "name": "大机构",
      "emoji": "🏦",
      "total_value": 38942.84,
      "cash": 13640.35,
      "position_value": 25302.49,
      "pnl": -11057.16,
      "return_pct": -22.11,
      "positions": 3
    },
    "aggressive": {
      "name": "激进交易",
      "emoji": "⚡",
      "total_value": 46362.45,
      "cash": 22338.85,
      "position_value": 24023.6,
      "pnl": -3637.55,
      "return_pct": -7.28,
      "positions": 5
    },
    "blueshrimp": {
      "name": "蓝虾交易",
      "emoji": "🦐",
      "total_value": 59654.53,
      "cash": 34102.14,
      "position_value": 25552.39,
      "pnl": 9654.53,
      "return_pct": 19.31,
      "positions": 4
    }
  }
}